[
  {
    "ID": 1,
    "Name": "Tony Bernardo",
    "Pronouns": "He/Him/His",
    "Instagram": "tonybernardo.art",
    "LinkedIn": "tonybernardo",
    "Website": "",
    "Program": "Illustration, Painting and Drawing",
    "Graduation": 2023,
    "Semester": "Fall",
    "Show": 1
  },
  {
    "ID": 2,
    "Name": "Claire Bivins",
    "Pronouns": "",
    "Instagram": "",
    "LinkedIn": "",
    "Website": "",
    "Program": "Ceramics",
    "Graduation": 2023,
    "Semester": "Fall",
    "Show": 1
  },
  {
    "ID": 3,
    "Name": "Tina bu",
    "Pronouns": "",
    "Instagram": "",
    "LinkedIn": "",
    "Website": "",
    "Program": "Jewelry and Metal Arts",
    "Graduation": 2023,
    "Semester": "Fall",
    "Show": 1
  },
  {
    "ID": 4,
    "Name": "Jonas Cohen",
    "Pronouns": "",
    "Instagram": "",
    "LinkedIn": "",
    "Website": "",
    "Program": "Furniture",
    "Graduation": 2023,
    "Semester": "Fall",
    "Show": 1
  },
  {
    "ID": 5,
    "Name": "Mengqi Li",
    "Pronouns": "she",
    "Instagram": "",
    "LinkedIn": "",
    "Website": "",
    "Program": "Painting and Drawing",
    "Graduation": 2023,
    "Semester": "Fall",
    "Show": 1
  },
  {
    "ID": 6,
    "Name": "Jiahui Luo",
    "Pronouns": "",
    "Instagram": "",
    "LinkedIn": "",
    "Website": "",
    "Program": "Jewelry and Metal Arts",
    "Graduation": 2023,
    "Semester": "Fall",
    "Show": 1
  },
  {
    "ID": 7,
    "Name": "James Aidan Newman",
    "Pronouns": "",
    "Instagram": "",
    "LinkedIn": "",
    "Website": "",
    "Program": "Writing and Literature",
    "Graduation": 2023,
    "Semester": "Fall",
    "Show": 1
  },
  {
    "ID": 8,
    "Name": "Baigexi Qi",
    "Pronouns": "",
    "Instagram": "",
    "LinkedIn": "",
    "Website": "",
    "Program": "Printmedia",
    "Graduation": 2023,
    "Semester": "Fall",
    "Show": 1
  },
  {
    "ID": 9,
    "Name": "Yaxuan Sussie Zhang",
    "Pronouns": "",
    "Instagram": "",
    "LinkedIn": "",
    "Website": "",
    "Program": "Jewelry and Metal Arts",
    "Graduation": 2023,
    "Semester": "Fall",
    "Show": 1
  },
  {
    "ID": 10,
    "Name": "Bryan Dominguez",
    "Pronouns": "",
    "Instagram": "bryans_arte",
    "LinkedIn": "",
    "Website": "Bryansarte.com",
    "Program": "Painting and Drawing",
    "Graduation": 2023,
    "Semester": "Fall",
    "Show": ""
  },
  {
    "ID": 11,
    "Name": "Emily Fernandes",
    "Pronouns": "",
    "Instagram": "",
    "LinkedIn": "",
    "Website": "",
    "Program": "Painting and Drawing",
    "Graduation": 2023,
    "Semester": "Fall",
    "Show": ""
  },
  {
    "ID": 12,
    "Name": "Demi Gao",
    "Pronouns": "",
    "Instagram": "",
    "LinkedIn": "",
    "Website": "",
    "Program": "Painting and Drawing",
    "Graduation": 2023,
    "Semester": "Fall",
    "Show": ""
  },
  {
    "ID": 13,
    "Name": "Yiwei Jiang (Jaen)",
    "Pronouns": "",
    "Instagram": "jannne_metalarts",
    "LinkedIn": "",
    "Website": "",
    "Program": "Jewelry and Metal Arts",
    "Graduation": 2023,
    "Semester": "Fall",
    "Show": ""
  },
  {
    "ID": 14,
    "Name": "Angela Lafko",
    "Pronouns": "",
    "Instagram": "",
    "LinkedIn": "",
    "Website": "",
    "Program": "Jewelry and Metal Arts",
    "Graduation": 2023,
    "Semester": "Fall",
    "Show": ""
  },
  {
    "ID": 15,
    "Name": "Emily Montes",
    "Pronouns": "",
    "Instagram": "",
    "LinkedIn": "",
    "Website": "",
    "Program": "Painting and Drawing",
    "Graduation": 2023,
    "Semester": "Fall",
    "Show": ""
  },
  {
    "ID": 16,
    "Name": "Zoe Segura",
    "Pronouns": "",
    "Instagram": "",
    "LinkedIn": "",
    "Website": "",
    "Program": "Sculpture",
    "Graduation": 2023,
    "Semester": "Fall",
    "Show": ""
  },
  {
    "ID": 17,
    "Name": "Faye Vavra",
    "Pronouns": "She/They",
    "Instagram": "faye_vav",
    "LinkedIn": "",
    "Website": "https://fayevavra.com/",
    "Program": "Painting and Drawing",
    "Graduation": 2023,
    "Semester": "Fall",
    "Show": ""
  }
]